{
  "data": {
    "article": {},
    "attachments": {},
    "author_id": "2055822314969665536",
    "conversation_id": "2071849059267318096",
    "created_at": "2026-06-30T09:13:29.000Z",
    "edit_controls": {
      "editable_until": "2026-06-30T10:13:29.000Z",
      "edits_remaining": 5,
      "is_edit_eligible": false
    },
    "edit_history_tweet_ids": [
      "2071884819022106719"
    ],
    "entities": {
      "mentions": [
        {
          "end": 12,
          "id": "2069131894957191168",
          "start": 0,
          "username": "Hemlock_114"
        }
      ]
    },
    "geo": {},
    "id": "2071884819022106719",
    "in_reply_to_user_id": "2069131894957191168",
    "lang": "zh",
    "note_tweet": {
      "entities": {}
    },
    "possibly_sensitive": false,
    "public_metrics": {
      "bookmark_count": 0,
      "impression_count": 0,
      "like_count": 0,
      "quote_count": 0,
      "reply_count": 0,
      "retweet_count": 0
    },
    "referenced_tweets": [
      {
        "id": "2071849059267318096",
        "type": "replied_to"
      }
    ],
    "reply_settings": "everyone",
    "text": "@Hemlock_114 我要穿人皮扣😭"
  },
  "includes": {
    "tweets": [
      {
        "article": {},
        "attachments": {},
        "author_id": "2055822314969665536",
        "conversation_id": "2071849059267318096",
        "created_at": "2026-06-30T09:13:29.000Z",
        "edit_controls": {
          "editable_until": "2026-06-30T10:13:29.000Z",
          "edits_remaining": 5,
          "is_edit_eligible": false
        },
        "edit_history_tweet_ids": [
          "2071884819022106719"
        ],
        "entities": {
          "mentions": [
            {
              "end": 12,
              "id": "2069131894957191168",
              "start": 0,
              "username": "Hemlock_114"
            }
          ]
        },
        "geo": {},
        "id": "2071884819022106719",
        "in_reply_to_user_id": "2069131894957191168",
        "lang": "zh",
        "note_tweet": {
          "entities": {}
        },
        "possibly_sensitive": false,
        "public_metrics": {
          "bookmark_count": 0,
          "impression_count": 0,
          "like_count": 0,
          "quote_count": 0,
          "reply_count": 0,
          "retweet_count": 0
        },
        "referenced_tweets": [
          {
            "id": "2071849059267318096",
            "type": "replied_to"
          }
        ],
        "reply_settings": "everyone",
        "text": "@Hemlock_114 我要穿人皮扣😭"
      },
      {
        "article": {},
        "attachments": {},
        "author_id": "2069131894957191168",
        "conversation_id": "2071849059267318096",
        "created_at": "2026-06-30T06:51:23.000Z",
        "edit_controls": {
          "editable_until": "2026-06-30T07:51:23.000Z",
          "edits_remaining": 5,
          "is_edit_eligible": true
        },
        "edit_history_tweet_ids": [
          "2071849059267318096"
        ],
        "entities": {},
        "geo": {},
        "id": "2071849059267318096",
        "lang": "zh",
        "note_tweet": {
          "entities": {}
        },
        "possibly_sensitive": false,
        "public_metrics": {
          "bookmark_count": 0,
          "impression_count": 334,
          "like_count": 12,
          "quote_count": 0,
          "reply_count": 3,
          "retweet_count": 0
        },
        "reply_settings": "everyone",
        "text": "我要去纹空针纹身 我要穿人皮扣 我要染头发！！"
      }
    ],
    "users": [
      {
        "created_at": "2026-05-17T01:27:33.000Z",
        "description": "同类互fo，成分请查看@aeglepotato/点赞狂魔/平时喜欢说怪话和发癫/备用@aeglepotato /🦋@aeglepotato /匿名提问箱https://t.co/C8vIKrLtCN",
        "entities": {
          "description": {
            "mentions": [
              {
                "end": 23,
                "start": 11,
                "username": "aeglepotato"
              },
              {
                "end": 54,
                "start": 42,
                "username": "aeglepotato"
              },
              {
                "end": 69,
                "start": 57,
                "username": "aeglepotato"
              }
            ],
            "urls": [
              {
                "display_url": "ngl.link/aeglepotato",
                "end": 99,
                "expanded_url": "https://ngl.link/aeglepotato",
                "start": 76,
                "url": "https://t.co/C8vIKrLtCN"
              }
            ]
          }
        },
        "id": "2055822314969665536",
        "name": "⛄ALLice🌈赛博幽灵",
        "pinned_tweet_id": "2064878659698102753",
        "profile_image_url": "https://pbs.twimg.com/profile_images/2067517312576421888/aGH7Myxd_normal.jpg",
        "protected": false,
        "public_metrics": {
          "followers_count": 175,
          "following_count": 250,
          "like_count": 7833,
          "listed_count": 0,
          "media_count": 14,
          "tweet_count": 488
        },
        "url": "",
        "username": "GrievousPotato1",
        "verified": false
      },
      {
        "created_at": "2026-06-22T18:56:04.000Z",
        "description": "🇭🇰 10 单机透明人🍋\noder｜🩸｜碎碎念｜小作文\n前世@Hemlock_113 (´；ω；｀)\n害怕社交 社交恐惧 只互fo同类\n接线下 不闲聊讨厌聊天拒绝聊天",
        "entities": {
          "description": {
            "mentions": [
              {
                "end": 42,
                "start": 30,
                "username": "Hemlock_113"
              }
            ]
          }
        },
        "id": "2069131894957191168",
        "name": "凝檬_☆2.0",
        "pinned_tweet_id": "2070124552861217225",
        "profile_image_url": "https://pbs.twimg.com/profile_images/2069134933218705408/DX0rO-YL_normal.jpg",
        "protected": false,
        "public_metrics": {
          "followers_count": 297,
          "following_count": 91,
          "like_count": 128,
          "listed_count": 0,
          "media_count": 16,
          "tweet_count": 225
        },
        "url": "",
        "username": "Hemlock_114",
        "verified": true
      }
    ]
  }
}