{
  "data": {
    "article": {},
    "attachments": {
      "media_keys": [
        "3_2064634074816245761"
      ]
    },
    "author_id": "2055822314969665536",
    "conversation_id": "2064668325855048042",
    "created_at": "2026-06-10T11:17:43.000Z",
    "edit_controls": {
      "editable_until": "2026-06-10T12:17:43.000Z",
      "edits_remaining": 5,
      "is_edit_eligible": true
    },
    "edit_history_tweet_ids": [
      "2064668325855048042"
    ],
    "entities": {
      "urls": [
        {
          "display_url": "pic.x.com/gS5pGPflVj",
          "end": 28,
          "expanded_url": "https://x.com/GrievousPotato1/status/2064668325855048042/photo/1",
          "media_key": "3_2064634074816245761",
          "start": 5,
          "url": "https://t.co/gS5pGPflVj"
        }
      ]
    },
    "geo": {},
    "id": "2064668325855048042",
    "lang": "zh",
    "note_tweet": {
      "entities": {}
    },
    "possibly_sensitive": false,
    "public_metrics": {
      "bookmark_count": 0,
      "impression_count": 0,
      "like_count": 0,
      "quote_count": 0,
      "reply_count": 0,
      "retweet_count": 0
    },
    "reply_settings": "everyone",
    "text": "剧烈变形 https://t.co/gS5pGPflVj"
  },
  "includes": {
    "media": [
      {
        "height": 636,
        "media_key": "3_2064634074816245761",
        "public_metrics": {},
        "type": "photo",
        "url": "https://pbs.twimg.com/media/HKcNwIyW8AEcaE7.jpg",
        "width": 1109
      }
    ],
    "tweets": [
      {
        "article": {},
        "attachments": {
          "media_keys": [
            "3_2064634074816245761"
          ]
        },
        "author_id": "2055822314969665536",
        "conversation_id": "2064668325855048042",
        "created_at": "2026-06-10T11:17:43.000Z",
        "edit_controls": {
          "editable_until": "2026-06-10T12:17:43.000Z",
          "edits_remaining": 5,
          "is_edit_eligible": true
        },
        "edit_history_tweet_ids": [
          "2064668325855048042"
        ],
        "entities": {
          "urls": [
            {
              "display_url": "pic.x.com/gS5pGPflVj",
              "end": 28,
              "expanded_url": "https://x.com/GrievousPotato1/status/2064668325855048042/photo/1",
              "media_key": "3_2064634074816245761",
              "start": 5,
              "url": "https://t.co/gS5pGPflVj"
            }
          ]
        },
        "geo": {},
        "id": "2064668325855048042",
        "lang": "zh",
        "note_tweet": {
          "entities": {}
        },
        "possibly_sensitive": false,
        "public_metrics": {
          "bookmark_count": 0,
          "impression_count": 0,
          "like_count": 0,
          "quote_count": 0,
          "reply_count": 0,
          "retweet_count": 0
        },
        "reply_settings": "everyone",
        "text": "剧烈变形 https://t.co/gS5pGPflVj"
      }
    ],
    "users": [
      {
        "created_at": "2026-05-17T01:27:33.000Z",
        "description": "同类回fo，至于是什么同类x不让我说/点赞狂魔，只互动不发推/查成分请翻回复or 去🦋 @aeglepotato / https://t.co/C8vIKrKVNf",
        "entities": {
          "description": {
            "mentions": [
              {
                "end": 56,
                "start": 44,
                "username": "aeglepotato"
              }
            ],
            "urls": [
              {
                "display_url": "ngl.link/aeglepotato",
                "end": 82,
                "expanded_url": "https://ngl.link/aeglepotato",
                "start": 59,
                "url": "https://t.co/C8vIKrKVNf"
              }
            ]
          }
        },
        "id": "2055822314969665536",
        "name": "🌈ALLice☃️赛博幽灵",
        "pinned_tweet_id": "2056519884301877431",
        "profile_image_url": "https://pbs.twimg.com/profile_images/2055823521440301056/FmjUDDvC_normal.jpg",
        "protected": false,
        "public_metrics": {
          "followers_count": 55,
          "following_count": 95,
          "like_count": 2811,
          "listed_count": 0,
          "media_count": 4,
          "tweet_count": 162
        },
        "username": "GrievousPotato1",
        "verified": false
      }
    ]
  }
}